loci_spotbugs/__init__.py
loci_spotbugs/main.py
loci_spotbugs/run.py
loci_spotbugs/summary.py
loci_spotbugs/utils.py
loci_spotbugs-0.1.0.dist-info/LICENSE
loci_spotbugs-0.1.0.dist-info/METADATA
loci_spotbugs-0.1.0.dist-info/WHEEL
loci_spotbugs-0.1.0.dist-info/entry_points.txt
loci_spotbugs-0.1.0.dist-info/top_level.txt
loci_spotbugs-0.1.0.dist-info/RECORD
