Metadata-Version: 2.1
Name: loci-spotbugs
Version: 0.1.0
Summary: The official Loci Notes SpotBugs results importer.
Home-page: https://gitlab.com/loci-notes/loci-spotbugs
Author: TheTwitchy
Author-email: thetwitchy@thetwitchy.com
License: UNKNOWN
Platform: UNKNOWN
License-File: LICENSE
Requires-Dist: click
Requires-Dist: requests
Requires-Dist: rich
Requires-Dist: defusedxml
